{
"meta":{"test_sets":[],"test_metrics":[],"learn_metrics":[{"best_value":"Min","name":"RMSE"}],"launch_mode":"Train","parameters":"","iteration_count":192,"learn_sets":["learn"],"name":"experiment"},
"iterations":[
{"learn":[41.04044853],"iteration":0,"passed_time":0.02270080176,"remaining_time":4.335853136},
{"learn":[39.45012814],"iteration":1,"passed_time":0.0427648657,"remaining_time":4.062662242},
{"learn":[37.99434173],"iteration":2,"passed_time":0.06414101161,"remaining_time":4.040883732},
{"learn":[36.6680058],"iteration":3,"passed_time":0.08493488422,"remaining_time":3.991939558},
{"learn":[35.48279121],"iteration":4,"passed_time":0.1032844491,"remaining_time":3.862838395},
{"learn":[34.32574609],"iteration":5,"passed_time":0.120375803,"remaining_time":3.731649892},
{"learn":[33.33393393],"iteration":6,"passed_time":0.1406267347,"remaining_time":3.716563702},
{"learn":[32.43949919],"iteration":7,"passed_time":0.1605349171,"remaining_time":3.692303094},
{"learn":[31.62125903],"iteration":8,"passed_time":0.1812803161,"remaining_time":3.686033094},
{"learn":[30.85244387],"iteration":9,"passed_time":0.1982338727,"remaining_time":3.607856483},
{"learn":[30.15187602],"iteration":10,"passed_time":0.2149021735,"remaining_time":3.536117582},
{"learn":[29.52630611],"iteration":11,"passed_time":0.2314858122,"remaining_time":3.472287183},
{"learn":[28.94400549],"iteration":12,"passed_time":0.2482478804,"remaining_time":3.418182354},
{"learn":[28.46048949],"iteration":13,"passed_time":0.2666715493,"remaining_time":3.39053827},
{"learn":[28.00331076],"iteration":14,"passed_time":0.2827680053,"remaining_time":3.336662463},
{"learn":[27.55660445],"iteration":15,"passed_time":0.2988223127,"remaining_time":3.287045439},
{"learn":[27.16343363],"iteration":16,"passed_time":0.3147808389,"remaining_time":3.240390989},
{"learn":[26.81080792],"iteration":17,"passed_time":0.3305960021,"remaining_time":3.195761353},
{"learn":[26.50946437],"iteration":18,"passed_time":0.3472529516,"remaining_time":3.161829507},
{"learn":[26.23796521],"iteration":19,"passed_time":0.3630040066,"remaining_time":3.121834457},
{"learn":[26.00249152],"iteration":20,"passed_time":0.3786372335,"remaining_time":3.083188901},
{"learn":[25.7743141],"iteration":21,"passed_time":0.3937489284,"remaining_time":3.042605356},
{"learn":[25.59321719],"iteration":22,"passed_time":0.4087927755,"remaining_time":3.00373822},
{"learn":[25.4128384],"iteration":23,"passed_time":0.4247072747,"remaining_time":2.972950923},
{"learn":[25.24052372],"iteration":24,"passed_time":0.4415666524,"remaining_time":2.949665238},
{"learn":[25.09646843],"iteration":25,"passed_time":0.4563670147,"remaining_time":2.913727863},
{"learn":[24.95819104],"iteration":26,"passed_time":0.4718030292,"remaining_time":2.883240734},
{"learn":[24.82919774],"iteration":27,"passed_time":0.4866332614,"remaining_time":2.850280531},
{"learn":[24.70430365],"iteration":28,"passed_time":0.5021968645,"remaining_time":2.822692721},
{"learn":[24.60083413],"iteration":29,"passed_time":0.5170921273,"remaining_time":2.792297487},
{"learn":[24.52068086],"iteration":30,"passed_time":0.5326140287,"remaining_time":2.76615673},
{"learn":[24.44330936],"iteration":31,"passed_time":0.5495012431,"remaining_time":2.747506216},
{"learn":[24.36952894],"iteration":32,"passed_time":0.5651732358,"remaining_time":2.723107409},
{"learn":[24.30406288],"iteration":33,"passed_time":0.5804886238,"remaining_time":2.697564781},
{"learn":[24.24026939],"iteration":34,"passed_time":0.596085125,"remaining_time":2.673867561},
{"learn":[24.1821991],"iteration":35,"passed_time":0.6115189751,"remaining_time":2.649915559},
{"learn":[24.11634068],"iteration":36,"passed_time":0.6276554022,"remaining_time":2.629367226},
{"learn":[24.06997502],"iteration":37,"passed_time":0.6429409046,"remaining_time":2.605602613},
{"learn":[24.00897283],"iteration":38,"passed_time":0.6587453543,"remaining_time":2.584308697},
{"learn":[23.97198312],"iteration":39,"passed_time":0.6767171437,"remaining_time":2.571525146},
{"learn":[23.93012218],"iteration":40,"passed_time":0.6934948219,"remaining_time":2.554090686},
{"learn":[23.88794338],"iteration":41,"passed_time":0.7107928315,"remaining_time":2.538545827},
{"learn":[23.85679362],"iteration":42,"passed_time":0.7275589802,"remaining_time":2.521076466},
{"learn":[23.82051466],"iteration":43,"passed_time":0.7450294371,"remaining_time":2.506008107},
{"learn":[23.78222431],"iteration":44,"passed_time":0.7627501791,"remaining_time":2.491650585},
{"learn":[23.75210068],"iteration":45,"passed_time":0.7821804317,"remaining_time":2.482572675},
{"learn":[23.72358175],"iteration":46,"passed_time":0.8009024776,"remaining_time":2.470869346},
{"learn":[23.70350796],"iteration":47,"passed_time":0.818662098,"remaining_time":2.455986294},
{"learn":[23.68283823],"iteration":48,"passed_time":0.8356440122,"remaining_time":2.438716199},
{"learn":[23.66233405],"iteration":49,"passed_time":0.8520768042,"remaining_time":2.419898124},
{"learn":[23.64354456],"iteration":50,"passed_time":0.8716040302,"remaining_time":2.409728789},
{"learn":[23.6041686],"iteration":51,"passed_time":0.8908974089,"remaining_time":2.398569947},
{"learn":[23.58201086],"iteration":52,"passed_time":0.9079483131,"remaining_time":2.381222934},
{"learn":[23.55970637],"iteration":53,"passed_time":0.9277033881,"remaining_time":2.370797547},
{"learn":[23.53565117],"iteration":54,"passed_time":0.9447042975,"remaining_time":2.353172523},
{"learn":[23.51625638],"iteration":55,"passed_time":0.9633065619,"remaining_time":2.339458793},
{"learn":[23.50003065],"iteration":56,"passed_time":0.9800155788,"remaining_time":2.321089529},
{"learn":[23.48801989],"iteration":57,"passed_time":0.9993369165,"remaining_time":2.308812876},
{"learn":[23.47537453],"iteration":58,"passed_time":1.019051796,"remaining_time":2.297184558},
{"learn":[23.46178664],"iteration":59,"passed_time":1.035496484,"remaining_time":2.278092264},
{"learn":[23.45195893],"iteration":60,"passed_time":1.051975571,"remaining_time":2.259160652},
{"learn":[23.43703321],"iteration":61,"passed_time":1.068114965,"remaining_time":2.239595894},
{"learn":[23.42672166],"iteration":62,"passed_time":1.087022575,"remaining_time":2.225808129},
{"learn":[23.40974538],"iteration":63,"passed_time":1.103673905,"remaining_time":2.20734781},
{"learn":[23.3975275],"iteration":64,"passed_time":1.121805112,"remaining_time":2.191834603},
{"learn":[23.39061434],"iteration":65,"passed_time":1.138190014,"remaining_time":2.172908209},
{"learn":[23.36998508],"iteration":66,"passed_time":1.155442753,"remaining_time":2.155676777},
{"learn":[23.35419769],"iteration":67,"passed_time":1.17451812,"remaining_time":2.141768336},
{"learn":[23.34560444],"iteration":68,"passed_time":1.19137098,"remaining_time":2.123748269},
{"learn":[23.33438376],"iteration":69,"passed_time":1.208585474,"remaining_time":2.106391826},
{"learn":[23.32415826],"iteration":70,"passed_time":1.227402744,"remaining_time":2.091770874},
{"learn":[23.30721639],"iteration":71,"passed_time":1.243528296,"remaining_time":2.072547159},
{"learn":[23.29858958],"iteration":72,"passed_time":1.261286066,"remaining_time":2.056069067},
{"learn":[23.28700966],"iteration":73,"passed_time":1.27840683,"remaining_time":2.038540621},
{"learn":[23.27964987],"iteration":74,"passed_time":1.295089173,"remaining_time":2.02033911},
{"learn":[23.26847938],"iteration":75,"passed_time":1.31195558,"remaining_time":2.002458517},
{"learn":[23.26031168],"iteration":76,"passed_time":1.329863491,"remaining_time":1.986159759},
{"learn":[23.24287288],"iteration":77,"passed_time":1.346247841,"remaining_time":1.967592998},
{"learn":[23.23403338],"iteration":78,"passed_time":1.36272488,"remaining_time":1.949214069},
{"learn":[23.22840368],"iteration":79,"passed_time":1.379471935,"remaining_time":1.931260709},
{"learn":[23.21847625],"iteration":80,"passed_time":1.399827818,"remaining_time":1.918282565},
{"learn":[23.21027237],"iteration":81,"passed_time":1.417019555,"remaining_time":1.900879891},
{"learn":[23.19705158],"iteration":82,"passed_time":1.433424689,"remaining_time":1.882449291},
{"learn":[23.19130399],"iteration":83,"passed_time":1.449395685,"remaining_time":1.863508738},
{"learn":[23.18403417],"iteration":84,"passed_time":1.465140594,"remaining_time":1.844353454},
{"learn":[23.17652013],"iteration":85,"passed_time":1.48101329,"remaining_time":1.825434986},
{"learn":[23.165446],"iteration":86,"passed_time":1.499863055,"remaining_time":1.810179549},
{"learn":[23.16048037],"iteration":87,"passed_time":1.516475565,"remaining_time":1.792198395},
{"learn":[23.15448548],"iteration":88,"passed_time":1.532225286,"remaining_time":1.773249488},
{"learn":[23.14852765],"iteration":89,"passed_time":1.548408019,"remaining_time":1.754862422},
{"learn":[23.14238283],"iteration":90,"passed_time":1.564960562,"remaining_time":1.73693425},
{"learn":[23.13632901],"iteration":91,"passed_time":1.582457751,"remaining_time":1.720062773},
{"learn":[23.12936456],"iteration":92,"passed_time":1.599351804,"remaining_time":1.702535791},
{"learn":[23.12035404],"iteration":93,"passed_time":1.616301143,"remaining_time":1.685079915},
{"learn":[23.1160438],"iteration":94,"passed_time":1.633865852,"remaining_time":1.668263027},
{"learn":[23.10906752],"iteration":95,"passed_time":1.650314554,"remaining_time":1.650314554},
{"learn":[23.10047132],"iteration":96,"passed_time":1.666776633,"remaining_time":1.632410105},
{"learn":[23.08777059],"iteration":97,"passed_time":1.685394163,"remaining_time":1.616602565},
{"learn":[23.07866057],"iteration":98,"passed_time":1.702515625,"remaining_time":1.59933286},
{"learn":[23.07152567],"iteration":99,"passed_time":1.71864146,"remaining_time":1.581150143},
{"learn":[23.06327391],"iteration":100,"passed_time":1.734390481,"remaining_time":1.562668651},
{"learn":[23.05286329],"iteration":101,"passed_time":1.752314272,"remaining_time":1.546159652},
{"learn":[23.04418089],"iteration":102,"passed_time":1.768795352,"remaining_time":1.528376566},
{"learn":[23.03826092],"iteration":103,"passed_time":1.785630184,"remaining_time":1.510917848},
{"learn":[23.02820388],"iteration":104,"passed_time":1.803674796,"remaining_time":1.494473402},
{"learn":[23.02344039],"iteration":105,"passed_time":1.822266543,"remaining_time":1.478442667},
{"learn":[23.01884308],"iteration":106,"passed_time":1.838927876,"remaining_time":1.460830556},
{"learn":[23.01225635],"iteration":107,"passed_time":1.856336069,"remaining_time":1.443816943},
{"learn":[23.00563625],"iteration":108,"passed_time":1.874714103,"remaining_time":1.427534593},
{"learn":[22.99874791],"iteration":109,"passed_time":1.892093027,"remaining_time":1.410469347},
{"learn":[22.98271458],"iteration":110,"passed_time":1.908806945,"remaining_time":1.392913176},
{"learn":[22.97190979],"iteration":111,"passed_time":1.926581232,"remaining_time":1.376129451},
{"learn":[22.96569601],"iteration":112,"passed_time":1.942697383,"remaining_time":1.358168967},
{"learn":[22.95224676],"iteration":113,"passed_time":1.960189315,"remaining_time":1.341182163},
{"learn":[22.94302905],"iteration":114,"passed_time":1.978339481,"remaining_time":1.324627304},
{"learn":[22.93692227],"iteration":115,"passed_time":1.997522009,"remaining_time":1.308721316},
{"learn":[22.93245398],"iteration":116,"passed_time":2.013804378,"remaining_time":1.290900242},
{"learn":[22.92994534],"iteration":117,"passed_time":2.031772959,"remaining_time":1.274162703},
{"learn":[22.92349545],"iteration":118,"passed_time":2.049337972,"remaining_time":1.257156907},
{"learn":[22.91355914],"iteration":119,"passed_time":2.066658524,"remaining_time":1.239995115},
{"learn":[22.90537371],"iteration":120,"passed_time":2.083838518,"remaining_time":1.222748222},
{"learn":[22.90216333],"iteration":121,"passed_time":2.101052619,"remaining_time":1.205521995},
{"learn":[22.89493648],"iteration":122,"passed_time":2.118441052,"remaining_time":1.188393761},
{"learn":[22.88520001],"iteration":123,"passed_time":2.136157907,"remaining_time":1.171441433},
{"learn":[22.88229729],"iteration":124,"passed_time":2.153182587,"remaining_time":1.154105867},
{"learn":[22.87310799],"iteration":125,"passed_time":2.171614791,"remaining_time":1.13751251},
{"learn":[22.86370486],"iteration":126,"passed_time":2.189037094,"remaining_time":1.120373316},
{"learn":[22.86011609],"iteration":127,"passed_time":2.205725083,"remaining_time":1.102862541},
{"learn":[22.84501651],"iteration":128,"passed_time":2.223047128,"remaining_time":1.085674179},
{"learn":[22.83855596],"iteration":129,"passed_time":2.239581377,"remaining_time":1.068108041},
{"learn":[22.83223084],"iteration":130,"passed_time":2.256038028,"remaining_time":1.050521525},
{"learn":[22.82625609],"iteration":131,"passed_time":2.272245899,"remaining_time":1.032839045},
{"learn":[22.82206244],"iteration":132,"passed_time":2.291009153,"remaining_time":1.016312331},
{"learn":[22.81583762],"iteration":133,"passed_time":2.307889142,"remaining_time":0.9989370912},
{"learn":[22.80942081],"iteration":134,"passed_time":2.324110879,"remaining_time":0.9812912601},
{"learn":[22.80694166],"iteration":135,"passed_time":2.340445822,"remaining_time":0.9637129857},
{"learn":[22.80547692],"iteration":136,"passed_time":2.35212438,"remaining_time":0.9442835103},
{"learn":[22.80237801],"iteration":137,"passed_time":2.369395756,"remaining_time":0.927154861},
{"learn":[22.79955325],"iteration":138,"passed_time":2.386384572,"remaining_time":0.9099164195},
{"learn":[22.79706214],"iteration":139,"passed_time":2.409433043,"remaining_time":0.8949322732},
{"learn":[22.78804032],"iteration":140,"passed_time":2.425353273,"remaining_time":0.8772554391},
{"learn":[22.77882662],"iteration":141,"passed_time":2.442951219,"remaining_time":0.8601940913},
{"learn":[22.77477306],"iteration":142,"passed_time":2.459618559,"remaining_time":0.8428063594},
{"learn":[22.7646257],"iteration":143,"passed_time":2.477529526,"remaining_time":0.8258431753},
{"learn":[22.75693884],"iteration":144,"passed_time":2.493829951,"remaining_time":0.8083448808},
{"learn":[22.74516024],"iteration":145,"passed_time":2.51216029,"remaining_time":0.791502557},
{"learn":[22.73598199],"iteration":146,"passed_time":2.528170702,"remaining_time":0.7739298068},
{"learn":[22.73109723],"iteration":147,"passed_time":2.546481015,"remaining_time":0.7570619233},
{"learn":[22.72766054],"iteration":148,"passed_time":2.563586545,"remaining_time":0.7398269896},
{"learn":[22.7177844],"iteration":149,"passed_time":2.579875239,"remaining_time":0.722365067},
{"learn":[22.7098986],"iteration":150,"passed_time":2.595666726,"remaining_time":0.7047836806},
{"learn":[22.69759272],"iteration":151,"passed_time":2.612656752,"remaining_time":0.6875412507},
{"learn":[22.69558556],"iteration":152,"passed_time":2.628787496,"remaining_time":0.6700830871},
{"learn":[22.69284815],"iteration":153,"passed_time":2.641946654,"remaining_time":0.6519089145},
{"learn":[22.67870463],"iteration":154,"passed_time":2.658591497,"remaining_time":0.6346315187},
{"learn":[22.67147187],"iteration":155,"passed_time":2.677542334,"remaining_time":0.6178943848},
{"learn":[22.66699943],"iteration":156,"passed_time":2.694854694,"remaining_time":0.6007637853},
{"learn":[22.66450685],"iteration":157,"passed_time":2.711117084,"remaining_time":0.5834049422},
{"learn":[22.65774263],"iteration":158,"passed_time":2.728802896,"remaining_time":0.566355318},
{"learn":[22.65082535],"iteration":159,"passed_time":2.747884152,"remaining_time":0.5495768304},
{"learn":[22.63834893],"iteration":160,"passed_time":2.765800101,"remaining_time":0.532545361},
{"learn":[22.63664854],"iteration":161,"passed_time":2.782709172,"remaining_time":0.5153165133},
{"learn":[22.62832399],"iteration":162,"passed_time":2.801523829,"remaining_time":0.4984306198},
{"learn":[22.61386131],"iteration":163,"passed_time":2.820614628,"remaining_time":0.4815683511},
{"learn":[22.60319289],"iteration":164,"passed_time":2.838764053,"remaining_time":0.4645250268},
{"learn":[22.58976448],"iteration":165,"passed_time":2.857857046,"remaining_time":0.4476161638},
{"learn":[22.58202042],"iteration":166,"passed_time":2.876801213,"remaining_time":0.4306588641},
{"learn":[22.57887002],"iteration":167,"passed_time":2.893869499,"remaining_time":0.4134099285},
{"learn":[22.57194421],"iteration":168,"passed_time":2.910372203,"remaining_time":0.3960861579},
{"learn":[22.56110808],"iteration":169,"passed_time":2.927416262,"remaining_time":0.3788421046},
{"learn":[22.55394674],"iteration":170,"passed_time":2.94583324,"remaining_time":0.3617689944},
{"learn":[22.55184771],"iteration":171,"passed_time":2.9667363,"remaining_time":0.3449693372},
{"learn":[22.54449897],"iteration":172,"passed_time":2.982239738,"remaining_time":0.3275292198},
{"learn":[22.53805518],"iteration":173,"passed_time":2.998732869,"remaining_time":0.3102137451},
{"learn":[22.53391294],"iteration":174,"passed_time":3.015366606,"remaining_time":0.2929213275},
{"learn":[22.52881566],"iteration":175,"passed_time":3.033817066,"remaining_time":0.2758015514},
{"learn":[22.51935693],"iteration":176,"passed_time":3.051492789,"remaining_time":0.2586010838},
{"learn":[22.51084222],"iteration":177,"passed_time":3.06770131,"remaining_time":0.2412798783},
{"learn":[22.50896636],"iteration":178,"passed_time":3.083696849,"remaining_time":0.2239556371},
{"learn":[22.50440325],"iteration":179,"passed_time":3.100807239,"remaining_time":0.2067204826},
{"learn":[22.49671158],"iteration":180,"passed_time":3.117012359,"remaining_time":0.1894316903},
{"learn":[22.48713491],"iteration":181,"passed_time":3.133753718,"remaining_time":0.1721842702},
{"learn":[22.48273275],"iteration":182,"passed_time":3.152117433,"remaining_time":0.1550221688},
{"learn":[22.47472642],"iteration":183,"passed_time":3.168767029,"remaining_time":0.1377724795},
{"learn":[22.47066072],"iteration":184,"passed_time":3.186864621,"remaining_time":0.1205840667},
{"learn":[22.46366542],"iteration":185,"passed_time":3.204619145,"remaining_time":0.1033748111},
{"learn":[22.45688828],"iteration":186,"passed_time":3.221597963,"remaining_time":0.08613898297},
{"learn":[22.45371537],"iteration":187,"passed_time":3.240504785,"remaining_time":0.06894691033},
{"learn":[22.44825562],"iteration":188,"passed_time":3.257826071,"remaining_time":0.05171152494},
{"learn":[22.44126985],"iteration":189,"passed_time":3.275117353,"remaining_time":0.03447491951},
{"learn":[22.43060245],"iteration":190,"passed_time":3.296813285,"remaining_time":0.01726080254},
{"learn":[22.42538421],"iteration":191,"passed_time":3.314674318,"remaining_time":0}
]}